other/index.html
xvs/__init__.py
xvs/cli.py
xvs/commit.py
xvs/core.py
xedix_versioning_system-0.1.2.dist-info/LICENSE
xedix_versioning_system-0.1.2.dist-info/METADATA
xedix_versioning_system-0.1.2.dist-info/WHEEL
xedix_versioning_system-0.1.2.dist-info/entry_points.txt
xedix_versioning_system-0.1.2.dist-info/top_level.txt
xedix_versioning_system-0.1.2.dist-info/RECORD
