Metadata-Version: 2.1
Name: xedix-versioning-system
Version: 0.1.2
Summary: A simple version control system
Author-email: Juraj Kollár <mostypc7@gmail.com>
Classifier: Programming Language :: Python :: 3
Classifier: Operating System :: OS Independent
Requires-Python: >=3.7
License-File: LICENSE
